pyfxgit/ChartCls.py
pyfxgit/__init__.py
pyfxgit-0.0.2.dist-info/METADATA
pyfxgit-0.0.2.dist-info/WHEEL
pyfxgit-0.0.2.dist-info/top_level.txt
pyfxgit-0.0.2.dist-info/RECORD
