Metadata-Version: 2.1
Name: pyfxgit
Version: 0.0.2
Summary: This is a package of helper classes and libraries.
Home-page: UNKNOWN
Author: Dennis Lee
Author-email: dennislwm@gmail.com
License: MIT
Platform: UNKNOWN
Requires-Dist: matplotlib ==3.2.2
Requires-Dist: mpl-finance
Requires-Dist: numpy ==1.18.5
Requires-Dist: pandas ==1.3.0
